footprint/__init__.py
footprint/cli.py
footprint/modules/__init__.py
footprint/modules/config.py
footprint/modules/github.py
footprint/modules/gitlab.py
footprint-0.1.1.dev0.dist-info/LICENSE
footprint-0.1.1.dev0.dist-info/METADATA
footprint-0.1.1.dev0.dist-info/WHEEL
footprint-0.1.1.dev0.dist-info/entry_points.txt
footprint-0.1.1.dev0.dist-info/top_level.txt
footprint-0.1.1.dev0.dist-info/RECORD
