Metadata-Version: 2.1
Name: footprint
Version: 0.1.1.dev0
Summary: footpritnt(足跡) is summary generator for Github/Gitlab.com activity.
Home-page: https://github.com/laughk/footprint
Author: Kei Iwasaki
Author-email: me@laughk.org
License: MIT License
Platform: UNKNOWN
Classifier: Development Status :: 2 - Pre-Alpha
Classifier: License :: OSI Approved :: MIT License
Classifier: Programming Language :: Python :: 3.6
Requires-Dist: PyGithub
Requires-Dist: python-dateutil
Requires-Dist: tzlocal
